enedis/__init__.py
enedis/client_proxy/__init__.py
enedis/client_proxy/client_proxy_enedis.py
enedis/connection/__init__.py
enedis/connection/enedis_connection.py
enedis/data_models/M023.py
enedis/data_models/__init__.py
enedis/data_models/commandeaccesdonneesmesures.py
enedis/data_models/commanderarretservicesouscritmesures.py
enedis/data_models/commandercollectepublicationmesures.py
enedis/data_models/common.py
enedis/data_models/const.py
enedis/data_models/consulterdonneespoint.py
enedis/data_models/consulterdonneestechniquescontractuelles.py
enedis/data_models/consultermesures.py
enedis/data_models/consultermesuresdetaillees.py
enedis/data_models/recherchepoint.py
enedis/data_models/rechercheservicesouscritmesures.py
enedis/examples/__init__.py
enedis/examples/m023_call.py
enedis/ressources/Dictionnaires/Metier/v4.0/ERDF.Dictionnaire.TypeComplexe.v4.0.xsd
enedis/ressources/Dictionnaires/Metier/v4.0/ERDF.Dictionnaire.TypeSimple.v4.0.xsd
enedis/ressources/Dictionnaires/Metier/v5.0/ENEDIS.Dictionnaire.TypeComplexe.v5.0.xsd
enedis/ressources/Dictionnaires/Metier/v5.0/ENEDIS.Dictionnaire.TypeSimple.v5.0.xsd
enedis/ressources/Dictionnaires/Technique/W3C.SoapEnv.xsd
enedis/ressources/Dictionnaires/Technique/v1.0/ENEDIS.Dictionnaire.Technique.v1.0.xsd
enedis/ressources/Services/CommandeArretServiceSouscritMesures/CommandeArretServiceSouscritMesures-v1.0.wsdl
enedis/ressources/Services/CommandeArretServiceSouscritMesures/CommanderArretServiceSouscritMesures-v1.0.xsd
enedis/ressources/Services/CommandeCollectePublicationMesures/CommandeCollectePublicationMesures-v3.0.wsdl
enedis/ressources/Services/CommandeCollectePublicationMesures/CommanderCollectePublicationMesures-v3.0.xsd
enedis/ressources/Services/CommanderAccesDonneesMesures/CommanderAccesDonneesMesures-V1.0.wsdl
enedis/ressources/Services/CommanderAccesDonneesMesures/CommanderAccesDonneesMesures-V1.0.xsd
wsenedis-0.6.1.dist-info/LICENSE
wsenedis-0.6.1.dist-info/METADATA
wsenedis-0.6.1.dist-info/WHEEL
wsenedis-0.6.1.dist-info/top_level.txt
wsenedis-0.6.1.dist-info/RECORD
