Metadata-Version: 2.2
Name: wsenedis
Version: 0.6.1
Summary: A module to communicate with Enedis webservices
Home-page: https://github.com/jplartigue/webservices-enedis
Author: Jean-Pierre Lartigue
Author-email: contact@holmium-consulting.com
License: BSD-3-Clause
Classifier: Environment :: Web Environment
Classifier: Framework :: Django
Classifier: Framework :: Django :: 4.2
Classifier: Intended Audience :: Developers
Classifier: License :: OSI Approved :: BSD License
Classifier: Operating System :: OS Independent
Classifier: Programming Language :: Python
Classifier: Programming Language :: Python :: 3
Classifier: Programming Language :: Python :: 3 :: Only
Classifier: Programming Language :: Python :: 3.10
Classifier: Programming Language :: Python :: 3.11
Classifier: Programming Language :: Python :: 3.12
Classifier: Topic :: Internet :: WWW/HTTP
Classifier: Topic :: Internet :: WWW/HTTP :: Dynamic Content
Requires-Python: >=3.10
License-File: LICENSE
Requires-Dist: Django<5.0.0,>=4.0.0
Requires-Dist: pandas<2.0.0,>=1.5.0
Requires-Dist: pyarrow>=14.0.0
Requires-Dist: packaging>=22.0
Requires-Dist: djangorestframework>=3.14.0
Requires-Dist: psycopg2-binary>=2.9.2
Requires-Dist: gunicorn>=20.1.0
Requires-Dist: requests>=2.31.0
Requires-Dist: zeep>=4.2.1
Requires-Dist: django-extensions>=3.2.0
Requires-Dist: boto3>=1.24.0
